pet_mad/__init__.py
pet_mad/_models.py
pet_mad/_version.py
pet_mad/calculator.py
pet_mad/modules.py
pet_mad/utils.py
pet_mad/explore/__init__.py
pet_mad/explore/_explorer.py
pet_mad/explore/_featurizer.py
pet_mad/explore/_modules.py
pet_mad-1.4.4.dist-info/licenses/LICENSE
pet_mad-1.4.4.dist-info/METADATA
pet_mad-1.4.4.dist-info/WHEEL
pet_mad-1.4.4.dist-info/top_level.txt
pet_mad-1.4.4.dist-info/RECORD
