Metadata-Version: 2.4
Name: pet-mad
Version: 1.4.4
Summary: A universal interatomic potential for advanced materials modeling
Author: Filippo Bigi, Matthias Kellner, Paolo Pegolo, Davide Tisi, Guillaume Fraux, Sergey Pozdnyakov, Philip Loche
Author-email: Arslan Mazitov <arslan.mazitov@epfl.ch>, Michele Ceriotti <michele.ceriotti@epfl.ch>
Maintainer-email: Arslan Mazitov <arslan.mazitov@epfl.ch>
License-Expression: BSD-3-Clause
Project-URL: repository, https://github.com/lab-cosmo/pet-mad
Keywords: machine learning,molecular modeling
Classifier: Development Status :: 4 - Beta
Classifier: Intended Audience :: Science/Research
Classifier: Operating System :: POSIX
Classifier: Operating System :: MacOS :: MacOS X
Classifier: Operating System :: Microsoft :: Windows
Classifier: Programming Language :: Python
Classifier: Programming Language :: Python :: 3
Classifier: Topic :: Scientific/Engineering
Classifier: Topic :: Scientific/Engineering :: Bio-Informatics
Classifier: Topic :: Scientific/Engineering :: Chemistry
Classifier: Topic :: Scientific/Engineering :: Physics
Classifier: Topic :: Software Development :: Libraries
Classifier: Topic :: Software Development :: Libraries :: Python Modules
Requires-Python: >=3.10
License-File: LICENSE
Requires-Dist: metatrain==2025.12
Requires-Dist: huggingface_hub
Requires-Dist: hf_xet
Requires-Dist: packaging
Requires-Dist: platformdirs
Requires-Dist: tqdm
Requires-Dist: scipy>=1.15.0
Provides-Extra: deprecated
Requires-Dist: pet-neighbors-convert; extra == "deprecated"
Requires-Dist: torch-geometric; extra == "deprecated"
Requires-Dist: matscipy; extra == "deprecated"
Requires-Dist: scikit-learn; extra == "deprecated"
Requires-Dist: pathos; extra == "deprecated"
Requires-Dist: scipy; extra == "deprecated"
Dynamic: license-file
